{
  "title": "Incantation",
  "release_date": "2021-08-18",
  "vote_average": 5.432,
  "genres": "Horror, Thriller",
  "overview": "As her life spirals out of control, a rebellious undergrad begins practicing a forbidden witchcraft to help her grades; but when she unknowingly unleashes a deadly curse that threatens her father's life, she will be forced to pass her biggest test yet.",
  "poster_path": "https://image.tmdb.org/t/p/w500/1l4hxdc7PyYgZ0DeZtC0WPU3GOI.jpg",
  "imdb_id": "tt10333688",
  "id": 1014659,
  "type": "movie"
}