{
  "title": "The Teacher Who Promised the Sea",
  "release_date": "2023-11-10",
  "vote_average": 7.6,
  "genres": "Drama, History",
  "overview": "Ariadna discovers that her grandfather has been searching for the remains of his father, who disappeared during the Civil War. Determined to help him, she travels to Burgos, where a mass grave is being excavated, and where he could be buried. During her stay there, she will learn the story of Antoni Benaiges, a young teacher from Tarragona who was her grandfather's teacher before the war. Through an innovative pedagogical method, Antoni inspired his students and made them a promise: to take them to see the sea.",
  "poster_path": "https://image.tmdb.org/t/p/w500/zprgWBLA9HSNHGowUEZRDJ3SXmC.jpg",
  "imdb_id": "tt11887316",
  "id": 1024541,
  "type": "movie"
}