{
  "title": "Suite Room",
  "release_date": "1993-01-01",
  "vote_average": 0,
  "genres": "Drama, Romance",
  "overview": "Ando Chigusa is the editor of 'Weekly Topaz'. She rented a room once a week to her female writer, Aso Tsuyoshi, as a place of affair. Chigusa was surprised to find out about the other person. It was Chigusa's ex-boyfriend, Shinjo Tsuyoshi...!!",
  "poster_path": "https://image.tmdb.org/t/p/w500/ntatAw1YVHjHgmu8QXSkzv7f8a.jpg",
  "imdb_id": null,
  "id": 1058283,
  "type": "movie"
}