{
  "title": "Trishul",
  "release_date": "1978-05-05",
  "vote_average": 6.4,
  "genres": "Action, Drama, Family",
  "overview": "Vijay Kumar is the illegitimate son of a construction baron, Raj Kumar Gupta and his first love, Shanti, whom Raj had given up in order to marry a wealthy heiress. Raj does not know of this son, who grows up and after his mother's death comes to Delhi to take revenge on the Gupta family by destroying the family's business and their relation with each other.",
  "poster_path": "https://image.tmdb.org/t/p/w500/zqf9mx1mNnWKw0ndISTsw672DJI.jpg",
  "imdb_id": "tt0078418",
  "id": 108016,
  "type": "movie"
}