{
  "title": "The Mysteries of Snæfellsjökull",
  "release_date": "2009-01-01",
  "vote_average": 0,
  "genres": "Documentary",
  "overview": "Some Icelanders maintain a strong and mysterious relationship with Snæfellsjökull, a volcano-glacier located in the West of the island. This volcano has become universally celebrated, thanks to Jules Verne who indicated that it was the gateway leading to the center of the Earth.",
  "poster_path": "https://image.tmdb.org/t/p/w500null",
  "imdb_id": "tt1508304",
  "id": 1094572,
  "type": "movie"
}