{
  "title": "Cats & Dogs",
  "release_date": "2001-07-04",
  "vote_average": 5.4,
  "genres": "Family, Comedy",
  "overview": "When a professor develops a vaccine that eliminates human allergies to dogs, he unwittingly upsets the fragile balance of power between cats and dogs and touches off an epic battle for pet supremacy. The fur flies as the feline faction, led by Mr. Tinkles, squares off against wide-eyed puppy Lou and his canine cohorts.",
  "poster_path": "https://image.tmdb.org/t/p/w500/azV3Je9uYKvSL2B46wc4vOHJV4S.jpg",
  "imdb_id": "tt0239395",
  "id": 10992,
  "type": "movie"
}