{
  "title": "French Fried Vacation",
  "release_date": "1978-11-11",
  "vote_average": 6.567,
  "genres": "Comedy",
  "overview": "Holidaymakers arriving in a Club Med camp on the Ivory Coast are determined to forget their everyday problems and emotional disappointments. Games, competitions, outings, bathing and sunburn accompany a continual succession of casual affairs.",
  "poster_path": "https://image.tmdb.org/t/p/w500/aUIne7L1aCBK64A6RvyAOcQzspQ.jpg",
  "imdb_id": "tt0077276",
  "id": 11183,
  "type": "movie"
}