{
  "title": "Black Dick In Me POV",
  "release_date": "2005-03-29",
  "vote_average": 0,
  "genres": "",
  "overview": "Imagine...your big black cock fucking 5 horny girls! Brooke stars in her first interracial scene - and she may never go back! She and four other girls take black dick as never before in their ready and willing mouths and cunts! Come join the ride as they are whisked away in a black tide of lust!",
  "poster_path": "https://image.tmdb.org/t/p/w500/6KFKw6y0t9WqkLBs2ZBLQuoImqH.jpg",
  "imdb_id": null,
  "id": 1134077,
  "type": "movie"
}