{
  "title": "Station Master",
  "release_date": "1942-05-09",
  "vote_average": 0,
  "genres": "Drama",
  "overview": "A railway employee, Kalicharan, would like Usha, the Station Master of Rangpur Railway Station's daughter, to get married to Niranjan, the DTS of Indian Railways, but Usha has fallen in love with Arun, a Guard with the Railway, wants to marry him, and refuses to marry Niranjan, who is twice as old as her and a widower as well.",
  "poster_path": "https://image.tmdb.org/t/p/w500/xMfBU1ednG2HxGUnxKb0ZXQxbTl.jpg",
  "imdb_id": "tt0035382",
  "id": 1194053,
  "type": "movie"
}