{
  "title": "June & John",
  "release_date": "2025-04-17",
  "vote_average": 6.3,
  "genres": "Romance, Thriller",
  "overview": "John leads an ordinary life with a monotonous routine. One day John runs into a woman on the subway who is as beautiful as she is mysterious named June. His encounter with her finally leads him to have a goal in his bumptious life.",
  "poster_path": "https://image.tmdb.org/t/p/w500/xRa3VBDf9RRz26SYtCTgOu9lQK2.jpg",
  "imdb_id": "tt20218618",
  "id": 1216571,
  "type": "movie"
}