{
  "title": "Not All Men, But...",
  "release_date": "2025-04-16",
  "vote_average": 6.1,
  "genres": "Comedy, Drama, Crime",
  "overview": "Simone, a cop with conservative ideas, infiltrates a feminist collective. However, her cover is thin. To divert attention and get out of this bad situation, Simone finds nothing better than to randomly accuse a man of having raped her.",
  "poster_path": "https://image.tmdb.org/t/p/w500/cpJuR5lgPewWVFs2N8o20rQ25AI.jpg",
  "imdb_id": "tt34997988",
  "id": 1235298,
  "type": "movie"
}