{
  "title": "Cursed Mountain - Green Inferno",
  "release_date": "2015-08-07",
  "vote_average": 0,
  "genres": "Horror",
  "overview": "A search party is organized to find people who have gone missing in the mountains. However, strange events begin to occur around them. One by one, the search party disappears. What awaits them in the end is an unbelievable truth!",
  "poster_path": "https://image.tmdb.org/t/p/w500/qxfUSuPSA6HU9oIob5HTwA1nfZf.jpg",
  "imdb_id": null,
  "id": 1250515,
  "type": "movie"
}