{
  "title": "Kachchi Kali",
  "release_date": "1987-07-12",
  "vote_average": 0,
  "genres": "Drama",
  "overview": "Sonika Gill plays an innocent virgin girl (Kachchi Kali as the title indicates) who is tricked by her lover (Ajinkya Deo) who is a blue film maker and sold off in to prostitution. Her brother (Alok Nath) tries hard to search for her in every brothel but in vain. Will he succeed in finding her?",
  "poster_path": "https://image.tmdb.org/t/p/w500/iTFcSPRqgox9fjL6Dr5MmkLxIr3.jpg",
  "imdb_id": "tt0476273",
  "id": 1276657,
  "type": "movie"
}