{
  "title": "Panor",
  "release_date": "2025-01-16",
  "vote_average": 5,
  "genres": "Horror, Thriller",
  "overview": "Panor, a young virgin, was born on the day when someone in the village performed a ritual to release black magic. Everyone despised her and accused her of being a bad omen. Anyone who was near her would suffer harm from black magic.",
  "poster_path": "https://image.tmdb.org/t/p/w500/fjvV2wQL8j7cgDVlR0Jru50UE16.jpg",
  "imdb_id": "tt35450281",
  "id": 1278162,
  "type": "movie"
}