{
  "title": "Cortina Express",
  "release_date": "2024-12-23",
  "vote_average": 5.4,
  "genres": "Comedy",
  "overview": "During Christmas holidays in Cortina d'Ampezzo, bon vivant Lucio tries to save his nephew from a marrying; faded rock sensation Dino wants his daughter's love back; and record producer Patrizia struggles with bankruptcy and a lazy husband.",
  "poster_path": "https://image.tmdb.org/t/p/w500/sxgk9pDIuHUmrZHHrR6gGyuPuyV.jpg",
  "imdb_id": "tt34371249",
  "id": 1294483,
  "type": "movie"
}