{
  "title": "Zamir & Preeti: a love story",
  "release_date": "2009-01-01",
  "vote_average": 0,
  "genres": "Drama, Family",
  "overview": "When riots between Hindus and Muslims erupt in India, a Hindu bride, Preeti, about to marry a Muslim man, Zamir, feels its repercussions all the way in the United States.  When the political becomes personal, can love rise above?",
  "poster_path": "https://image.tmdb.org/t/p/w500/ag7JPSN7pNmwcr2ZxQht7hNcge5.jpg",
  "imdb_id": null,
  "id": 1317685,
  "type": "movie"
}