{
  "title": "Ghost in the Shell: Hard-Wired Humanity - Making Ghost in the Shell",
  "release_date": "2017-07-25",
  "vote_average": 0,
  "genres": "Documentary",
  "overview": "An in depth look behind the scenes at the making of the live action Ghost In The Shell. Director Rupert Sanders, along with the cast and crew, take you from adapting the script and casting, production design and filming.",
  "poster_path": "https://image.tmdb.org/t/p/w500/we0VJKijVmKTF5UtJv2eXy8abSr.jpg",
  "imdb_id": "tt7182244",
  "id": 1319463,
  "type": "movie"
}