{
  "title": "Raktatilak",
  "release_date": "1974-02-15",
  "vote_average": 0,
  "genres": "Drama, Crime",
  "overview": "Master Roop Singh in disguise leads a band of dacoits in Madhya Pradesh. He has a change of heart at one point while hiding from the police and after a series of incidents involving his humanitarian feelings, he tries to surrender to the police but in the process many of his men die and Roop Singh survives.",
  "poster_path": "https://image.tmdb.org/t/p/w500/wO3M3urRULcKDN7UUF3Bo20KhYl.jpg",
  "imdb_id": "tt3874486",
  "id": 1340913,
  "type": "movie"
}