{
  "title": "Moon Maidens 2",
  "release_date": "2024-11-11",
  "vote_average": 1,
  "genres": "Science Fiction, Comedy",
  "overview": "A compilation film that has amazons invading Earth, encountering males and facing challenges. Amid media attention, rivals Diana and Athena strive to reunite before heading back to Byphrexia. Will they return safely or become Earth’s newest stars? Watch as the cosmic clash unfolds!",
  "poster_path": "https://image.tmdb.org/t/p/w500/8gK0VrxSDp06rOeIr2eaPHDoa1u.jpg",
  "imdb_id": "tt34563934",
  "id": 1394520,
  "type": "movie"
}