{
  "title": "Lusty Neighbors",
  "release_date": "1969-01-01",
  "vote_average": 2.5,
  "genres": "Romance",
  "overview": "A twenty-something brunette confesses her marital problems to her sexy, blonde neighbor.  The blonde suggests that the mousy, shy brunette attend her weekend \"swinging\" parties.  Five sex parties later leads to her mental breakdown and a visit from the local police!",
  "poster_path": "https://image.tmdb.org/t/p/w500/AcQ4fQaK0QdRL3W33Cl7WfEV3jQ.jpg",
  "imdb_id": "tt1553386",
  "id": 154459,
  "type": "movie"
}