{
  "title": "Woman Is the Future of Man",
  "release_date": "2004-05-05",
  "vote_average": 6.1,
  "genres": "Drama, Romance",
  "overview": "As the first snow falls in Seoul, two old friends reunite; one is a successful college professor, and the other, a struggling filmmaker recently returned from the United States. After their reminiscences, they finally decide to go in search of the young woman each had romanced years earlier.",
  "poster_path": "https://image.tmdb.org/t/p/w500/3bovtjGw5XB3aDKaWkfYnCupBbI.jpg",
  "imdb_id": "tt0403692",
  "id": 16447,
  "type": "movie"
}