{
  "title": "WWF Fully Loaded 2000",
  "release_date": "2000-07-23",
  "vote_average": 8.6,
  "genres": "Action, Drama",
  "overview": "The 2000 Fully Loaded was the third annual and final Fully Loaded professional wrestling pay-per-view (PPV) event produced by the World Wrestling Federation (WWF, now WWE). It took place on July 23, 2000, at the Reunion Arena in Dallas, Texas.",
  "poster_path": "https://image.tmdb.org/t/p/w500/1TuQquOB9dQyxAPYq4R838eK2GW.jpg",
  "imdb_id": "tt0269252",
  "id": 215449,
  "type": "movie"
}