{
  "title": "WIND BREAKER",
  "release_date": "2024-04-05",
  "vote_average": 8.2,
  "genres": "Animation, Action & Adventure",
  "overview": "Haruka Sakura wants nothing to do with weaklings—he's only interested in the strongest of the strong. He's just started at Furin High School, a school of degenerates known only for their brawling strength—strength they use to protect their town from anyone who wishes it ill. But Haruka's not interested in being a hero or being part of any sort of team—he just wants to fight his way to the top!",
  "poster_path": "https://image.tmdb.org/t/p/w500/3kTFL3PAeTyS8gGZAh0iYG6NNjt.jpg",
  "imdb_id": "NO ID",
  "id": 223500,
  "type": "tv"
}