{
  "title": "Revamp: The Undead Story",
  "release_date": "NO DATE",
  "vote_average": "NO RATING",
  "genres": "Mystery, Drama",
  "overview": "Punn, the owner of a vintage shop, is enlisted by a gallery-owning friend to restore a painting vandalised under mysterious circumstances. During the process, Punn injures himself, inadvertently staining the artwork with his blood. The act awakens Ramil, the last descendant of a vampire lineage, trapped within the painting for over a century. However, Ramil emerges powerless and becomes the target of relentless pursuit by the Hunters. Tasked with aiding Ramil in reclaiming his lost powers, Punn embarks on a journey to locate Ramil's former servants, now living discreetly among humans.",
  "poster_path": "https://image.tmdb.org/t/p/w500/bErPR6lUN2QDXW5KYXqseOKCtO9.jpg",
  "imdb_id": "NO ID",
  "id": 240144,
  "type": "tv"
}