{
  "title": "Our Land",
  "release_date": "1979-03-23",
  "vote_average": 0,
  "genres": "Drama",
  "overview": "Set between 1945 and 1951 in the pre-Independence state of Hyderabad, the film tells the story of a young peasant, Ramiah, who rebels against the corrupt rule of the Nizam. Baring witness to the oppression and hardship faced daily by those around him, Ramiah leaves his village. However, after befriending a Marxist activist and participating in the Independence struggle, he eventually returns to wage guerilla warfare against the landlord class.",
  "poster_path": "https://image.tmdb.org/t/p/w500/8spSB6PfJQx5QIYLYnkwnk84tu.jpg",
  "imdb_id": "tt0137925",
  "id": 260782,
  "type": "movie"
}