{
  "title": "Vaalu",
  "release_date": "2015-08-14",
  "vote_average": 4.75,
  "genres": "Comedy, Romance",
  "overview": "Sharp (Simbu), a happy-go-lucky guy, loves Priya (Hansika), a college student, but later learns that she is enagaged to Anbu ( Aditya), a businessman-gangster. Priya wants them to remain friends and Sharp agrees, all the while scheming to make her fall in love with him.",
  "poster_path": "https://image.tmdb.org/t/p/w500/cQ3MxP5yrMfdjSwVq2hjW5oRWKy.jpg",
  "imdb_id": "tt3566698",
  "id": 260778,
  "type": "movie"
}