{
  "title": "Chandrolsavam",
  "release_date": "2005-04-14",
  "vote_average": 4.5,
  "genres": "Drama",
  "overview": "You can't always turn back time. Circumstances force Sreehari (Mohanlal) to leave his village. He returns after several years as a successful Paris-based musician. While he tries to catch up on the time he has lost away from his village, he finds that things have changed - his former sweetheart is now married to someone else.",
  "poster_path": "https://image.tmdb.org/t/p/w500/q143ciY7c2olsrkKopAwXV0772v.jpg",
  "imdb_id": "tt0448408",
  "id": 280190,
  "type": "movie"
}