{
  "title": "What's the Time, Mr. Clock?",
  "release_date": "1985-08-14",
  "vote_average": 0,
  "genres": "War, Drama",
  "overview": "Even without a clock, the watch-maker of the small country town always knows the exact time to the second, and for this reason he came to be called Mr. Clock. His wife left him, and he only lives for his work. He is just engaged in repairing the tower clock when his wife returns and the German troops appear.",
  "poster_path": "https://image.tmdb.org/t/p/w500/l1Q8ranwHxNs5EQZg1GVq7Fne1q.jpg",
  "imdb_id": "tt0089315",
  "id": 286783,
  "type": "movie"
}