{
  "title": "Live Nude Girls",
  "release_date": "2014-08-19",
  "vote_average": 4.8,
  "genres": "Comedy, Romance",
  "overview": "When Shane inherits a gentleman's club from his estranged uncle, he leaves his Midwestern home for Los Angeles. Run by a booze hound and employing a dozen out of control strippers, Shane must do everything he can to save the club from bankruptcy and maybe make history in the process.",
  "poster_path": "https://image.tmdb.org/t/p/w500/cpXJk2chXIAlKUO17STos6DEjAZ.jpg",
  "imdb_id": "tt2946498",
  "id": 291326,
  "type": "movie"
}