{
  "title": "The Cannibal Man",
  "release_date": "1972-04-13",
  "vote_average": 6.3,
  "genres": "Drama, Horror, Thriller",
  "overview": "A young man, Marco, working as a butcher, accidentally kills a taxi driver. His girlfriend Paula wants to go to the police so he has to kill her too. He then has to kill his brother, his brother’s fiancée and his father, who have become suspicious. He gets rid of the bodies by taking them to a slaughter house.",
  "poster_path": "https://image.tmdb.org/t/p/w500/A2srdcBbijsL8wzfy9HM87NaVji.jpg",
  "imdb_id": "tt0067732",
  "id": 29336,
  "type": "movie"
}