{
  "title": "Naa Autograph",
  "release_date": "2004-08-11",
  "vote_average": 6.6,
  "genres": "Family, Romance, Drama",
  "overview": "Naa Autograph (English: My Autograph) is a 2004 Tollywood film directed by S. Gopal Reddy. The film stars Ravi Teja as the protagonist, with Bhumika Chawla, Gopika, Mallika and Prakash Raj playing other important roles. The film is a remake of the superhit Tamil film Autograph which starred Cheran and Sneha in the lead roles.",
  "poster_path": "https://image.tmdb.org/t/p/w500/s9iOis3DNbuyADpKCqpL9MAH8jK.jpg",
  "imdb_id": "tt0959328",
  "id": 307907,
  "type": "movie"
}