{
  "title": "C.B. Hustlers",
  "release_date": "1976-12-20",
  "vote_average": 2.2,
  "genres": "Comedy",
  "overview": "A group of prostitutes take their bordello on the road, loading into a van and using their CB radio to inform truckers of when and where they'll be stopping. The fun-loving girls enjoy success with their mobile brothel until they cross the state line into the Bible belt and find themselves under pursuit by the police.",
  "poster_path": "https://image.tmdb.org/t/p/w500/unJI05jnHcKzVNpChyW3uTQJcrn.jpg",
  "imdb_id": "tt0310837",
  "id": 30835,
  "type": "movie"
}