{
  "title": "...And Give Us Our Daily Sex",
  "release_date": "1979-02-26",
  "vote_average": 5.9,
  "genres": "Comedy",
  "overview": "A pair of sexy bisexual nurses live in an apartment building, one floor up from a middle-aged couple and their son Albert, who is busy putting his new science project—a periscope—to good use by spying on the lingerie-wearing lovelies. Meanwhile, Albert’s mother is being even naughtier than her precious boy, sneaking off for some extra-marital action while her hair-obsessed husband is at the salon, having his follicles tended to.",
  "poster_path": "https://image.tmdb.org/t/p/w500/kSWnoWhFUNrVSRaHM4dYtXbtaGX.jpg",
  "imdb_id": "tt0079515",
  "id": 30900,
  "type": "movie"
}