{
  "title": "Endless Poetry",
  "release_date": "2016-03-23",
  "vote_average": 7.5,
  "genres": "Fantasy, Drama",
  "overview": "A portrait of Alejandro Jodorowsky’s young adulthood, set in the 1940s and 50s, in the electric capital city of Santiago. There, he decides to become a poet and is introduced, by destiny, into the foremost bohemian and artistic circle of the time.",
  "poster_path": "https://image.tmdb.org/t/p/w500/iJTWnSa3YOnD15zMME3ox9GP8XA.jpg",
  "imdb_id": "tt4451458",
  "id": 325385,
  "type": "movie"
}