{
  "title": "Land of Mine",
  "release_date": "2015-12-03",
  "vote_average": 7.798,
  "genres": "War, Drama, History",
  "overview": "In the days following the surrender of Germany in May 1945, a group of young German prisoners of war is handed over to the Danish authorities and subsequently sent to the West Coast, where they are ordered to remove the more than two million mines that the Germans had placed in the sand along the coast. With their bare hands, crawling around in the sand, the boys are forced to perform the dangerous work under the leadership of a Danish sergeant.",
  "poster_path": "https://image.tmdb.org/t/p/w500/7TOYH2VDnYbXpBKlrkdQZUSC3Du.jpg",
  "imdb_id": "tt3841424",
  "id": 335578,
  "type": "movie"
}