{
  "title": "I Want To Be An American",
  "release_date": "2013-01-21",
  "vote_average": 10,
  "genres": "",
  "overview": "In the spirit of the Surrealist parlor game of chance Exquisite Corpse, each filmmaker makes a documentary short film based on imagery forwarded on by the previous filmmaker in the chain. The composite story forms a global independent filmmaking experience.",
  "poster_path": "https://image.tmdb.org/t/p/w500/8UmjWUzhBTBKMIOabGrtc5PtNQS.jpg",
  "imdb_id": "tt2702670",
  "id": 340867,
  "type": "movie"
}