{
  "title": "Hands of Lightning",
  "release_date": "1982-02-20",
  "vote_average": 0,
  "genres": "Action",
  "overview": "Baek-Chun, Baek-Ryong, and Baek-Ran lost their father. Aimless and wandering the streets, they find trouble with Paeng's gang who works for the nobleman, Jin. How far will the gangster go, and who will help the siblings against the gangsters?",
  "poster_path": "https://image.tmdb.org/t/p/w500/uqlTCH3Lb4NtccB57mKd3UH5r2R.jpg",
  "imdb_id": "",
  "id": 350117,
  "type": "movie"
}