{
  "title": "Again Kasarkode Khaderbai",
  "release_date": "2010-12-03",
  "vote_average": 1.625,
  "genres": "Comedy",
  "overview": "A group of mimicry artists is suspected when the son of an old nemesis is found murdered. A mimicry group called Kaladarshana are invited to perform in a jail. Incidentally, Kasim, the son of their old nemesis, Khader Bhai, is in the same jail. When Kasim is found murdered, the needle of suspicion points towards the group. Who is the real killer?",
  "poster_path": "https://image.tmdb.org/t/p/w500/lbvjAo6259rjnqI0IvgY5juxVGP.jpg",
  "imdb_id": "tt1869252",
  "id": 384029,
  "type": "movie"
}