{
  "title": "The Amityville Curse",
  "release_date": "1990-05-07",
  "vote_average": 3.942,
  "genres": "Horror, Thriller",
  "overview": "After purchasing a property in Amityville, New York, Debbie and her husband invite three of their closest friends to help renovate. Immediately uneasy in her new surroundings, she begins experiencing shockingly vivid nightmares.",
  "poster_path": "https://image.tmdb.org/t/p/w500/bGTF4uusklWxN0kBBe3msPKPCrb.jpg",
  "imdb_id": "tt0099030",
  "id": 41848,
  "type": "movie"
}