{
  "title": "Mafia Raaj",
  "release_date": "1998-12-10",
  "vote_average": 0,
  "genres": "",
  "overview": "Inspector Suraj (Mithun) is successful in maintaining peace and order in his village and is hence promoted to the city to keep the Mafia under control. Suraj moves to the city along with her sister, Chanda. In the city he crosses path with dangerous underworld dons Dhapat Jackal and his brother Jacky Jackal. To teach Suraj a lesson, the duo rape his sister and kill his father. Will Suraj have to go againstthe law to get his family justice? Will he succeed in taking revenge? Will he bring peace in the city as he did in his village?",
  "poster_path": "https://image.tmdb.org/t/p/w500null",
  "imdb_id": "tt2742196",
  "id": 425749,
  "type": "movie"
}