{
  "title": "Earth Defense Widow",
  "release_date": "2014-02-08",
  "vote_average": 4,
  "genres": "Comedy, Science Fiction",
  "overview": "Dan is a former geisha, now working as an ace pilot for the Earth Defense Troops. Her fiance was killed by the space monster Bemurasu which consumes nuclear waste. To save Planet Earth, Dan attacks Bemurasu, but whenever she does, she feels ecstasy. Can she save Planet Earth?",
  "poster_path": "https://image.tmdb.org/t/p/w500/gcFgtCALfIuLA7V864qfivqFZhw.jpg",
  "imdb_id": "tt3311564",
  "id": 435139,
  "type": "movie"
}