{
  "title": "Heart Blackened",
  "release_date": "2017-11-02",
  "vote_average": 7,
  "genres": "Crime, Thriller, Drama",
  "overview": "A father goes all out to clear his daughter from any wrong doing in the murder of his fiancée. When all evidence points to her, he takes matters into to his own hands to save his daughter and outwit the judiciary system.",
  "poster_path": "https://image.tmdb.org/t/p/w500/7CRwdPyw3vYwMApBr87vXcjwr67.jpg",
  "imdb_id": "tt7609180",
  "id": 437078,
  "type": "movie"
}