{
  "title": "My Brother's Lover",
  "release_date": "1998-08-27",
  "vote_average": 4.5,
  "genres": "",
  "overview": "Kenji breaks up with his girlfriend and goes to stay with his brother, Ryosuke, who is married but is having an affair with a local waitress.  It becomes clear quickly that Ryosuke is unhappy with his marriage to Haruyo, who desperately tries to get them to reconnect.  One night Kenji goes out alone, to see the mistress of his brother...and they fool around.",
  "poster_path": "https://image.tmdb.org/t/p/w500/djayrnWmh27WsPP2k7CwfNzDcmf.jpg",
  "imdb_id": "tt1781825",
  "id": 461926,
  "type": "movie"
}