{
  "title": "Balloon",
  "release_date": "2018-09-27",
  "vote_average": 7.5,
  "genres": "Thriller, Drama, History",
  "overview": "Two families attempt a daredevil plan to escape the GDR with a homemade hot air balloon, but it crashes just before the border. The Stasi finds traces of this attempt to escape and immediately starts investigations, while the two families are forced to build a new escape balloon. With each passing day the Stasi is closer on their heels – a nerve-wracking race against time begins.",
  "poster_path": "https://image.tmdb.org/t/p/w500/nRs8A0zp0jU211j8Zay3ApIzlpx.jpg",
  "imdb_id": "tt7125774",
  "id": 483983,
  "type": "movie"
}