{
  "title": "PAW Patrol: Halloween Heroes",
  "release_date": "2017-09-18",
  "vote_average": 8.9,
  "genres": "Animation",
  "overview": "Gear up for tricks, treats, and rescues in these 7 Halloween PAW Patrol adventures, featuring a really ghoul double-length special! Join a costume caper on Cap'n Turbot's haunted ship, track down a mysterious ghost, explore a creepy cabin, help a lost baby bat, save a pumpkin patch, stop a corn maze catastrophe and more!",
  "poster_path": "https://image.tmdb.org/t/p/w500/41StfADamaYwOBHQIaJhNp5yEVX.jpg",
  "imdb_id": null,
  "id": 486678,
  "type": "movie"
}