{
  "title": "Attack on Titan: The Roar of Awakening",
  "release_date": "2018-01-13",
  "vote_average": 8.4,
  "genres": "Animation, Action, Adventure, Fantasy",
  "overview": "Eren Yeager and others of the 104th Training Corps have just begun to become full members of the Survey Corps. As they ready themselves to face the Titans once again, their preparations are interrupted by the invasion of Wall Rose—but all is not as it seems as more mysteries are unraveled. As the Survey Corps races to save the wall, they uncover more about the invading Titans and the dark secrets of their own members.",
  "poster_path": "https://image.tmdb.org/t/p/w500/tLkdCvfmTOvxirrpSaaOBJD7qsU.jpg",
  "imdb_id": "tt7941892",
  "id": 492999,
  "type": "movie"
}