{
  "title": "Black Sun: The Nanking Massacre",
  "release_date": "1995-07-07",
  "vote_average": 6.125,
  "genres": "Drama, History, Horror, Thriller, War",
  "overview": "Black Sun: The Nanking Massacre depicts the brutal events behind the Nanking Massacre committed by the Imperial Japanese army against the Chinese people during the Second Sino-Japanese War.",
  "poster_path": "https://image.tmdb.org/t/p/w500/zxDxcrXzJzZLzEkk0MNozzKiAzi.jpg",
  "imdb_id": "tt0113281",
  "id": 51007,
  "type": "movie"
}