{
  "title": "Stalked by My Doctor: Patient's Revenge",
  "release_date": "2018-06-10",
  "vote_average": 6.3,
  "genres": "Thriller, TV Movie, Horror",
  "overview": "After being found not guilty for his crimes, Dr. Albert Beck takes a teaching job at a university, where his blossoming relationship with a student is threatened when one of his previous victims begins a campaign of terror against him.",
  "poster_path": "https://image.tmdb.org/t/p/w500/gUoTgAGg2zLW6aDItatY9h0x7xx.jpg",
  "imdb_id": "tt8499212",
  "id": 533274,
  "type": "movie"
}