{
  "title": "Fireflies",
  "release_date": "2018-10-21",
  "vote_average": 5.926,
  "genres": "Drama",
  "overview": "Ramin flees from persecution in Iran and ends up living in the limbo of exile, far from everything he knows, in the tropical port town of Veracruz, Mexico. There his nostalgia and melancholy are confronted with new friendships, while he starts to rediscover his own desires.",
  "poster_path": "https://image.tmdb.org/t/p/w500/2WAF6eqT7e2i0mpQkj11dkB3ipz.jpg",
  "imdb_id": "tt8159302",
  "id": 553779,
  "type": "movie"
}