{
  "title": "The World of Sexual Variations 2",
  "release_date": "2006-01-06",
  "vote_average": 0,
  "genres": "",
  "overview": "Well, your search has ended!  Get a heapin' helping of some of the strangest sexual appetites on the face of the planet! We've built this collection from the ground-up with plenty of pudding-poppin' scenes that are sure to maximize your meat mallet!  No matter what your particular tastes my be, there's plenty for the \"freak\" in everyone to enjoy in The World of Sexual Variations #2!",
  "poster_path": "https://image.tmdb.org/t/p/w500/3qhQQLtCTMZk5W0TEIXrLvOUl33.jpg",
  "imdb_id": "tt0862874",
  "id": 556957,
  "type": "movie"
}