{
  "title": "Hero - Bhakti Hi Shakti Hai",
  "release_date": "2005-05-30",
  "vote_average": 5.7,
  "genres": "Action & Adventure, Kids, Sci-Fi & Fantasy",
  "overview": "Hero - Bhakti Hi Shakti Hai is an Indian television show that aired from 2005 to 2007. blending action, fantasy, and devotional themes. The story revolved around a young boy named Joy who transforms into Hero, a superhero, using divine powers granted by goddess Durga to fight evil forces.",
  "poster_path": "https://image.tmdb.org/t/p/w500/xWX66szqmnGFokRzdZJtqCB2paG.jpg",
  "imdb_id": "NO ID",
  "id": 59041,
  "type": "tv"
}