{
  "title": "Around the World with Fanny Hill",
  "release_date": "1974-01-20",
  "vote_average": 3.6,
  "genres": "Comedy",
  "overview": "In Stockholm, Fanny Hill is tired of being a housewife, and she suspects that her husband Roger, a TV-commercial director who's surrounded by starlets, is cheating on her. So, she sets a trap for him with her friend Monica, files for divorce, and heads to Hollywood, with Monica, to meet film stars. She falls into a film career, with lots of nude scenes, and as it takes her from L.A. to Hong Kong and Venice, Roger follows her, jealous, hoping to win her back. In every city, she acts and she seduces, making comedy out of both; but does her heart still belong to Roger? It's on to Munich to find out.",
  "poster_path": "https://image.tmdb.org/t/p/w500/6zLz8tKPeRQm2Up4zdSB6UarAiV.jpg",
  "imdb_id": "tt0073212",
  "id": 60088,
  "type": "movie"
}