{
  "title": "L.O.R.D: Legend of Ravaging Dynasties 2",
  "release_date": "2020-12-02",
  "vote_average": 5.2,
  "genres": "Action, Adventure, War, Animation",
  "overview": "An upcoming Chinese computer animated motion capture action fantasy adventure film written and directed by Guo Jing Ming, the sequel to the first L.O.R.D: Legend of Ravaging Dynasties film.",
  "poster_path": "https://image.tmdb.org/t/p/w500/43MlbzxB5OohgvPHmPIvRi4MCVn.jpg",
  "imdb_id": "tt10701926",
  "id": 630044,
  "type": "movie"
}