{
  "title": "Sri Krishnadevaraya",
  "release_date": "1970-01-29",
  "vote_average": 9,
  "genres": "History, Drama",
  "overview": "Sri Krishnadevaraya is a 1970 Indian historical drama film in Kannada language, produced and directed by B. R. Panthulu. It stars Rajkumar as Krishnadevaraya, an emperor of the Vijayanagara Empire in the 16th century. R. Nagendra Rao, B. R. Panthulu, Narasimharaju and N. Bharathi appear in pivotal roles.",
  "poster_path": "https://image.tmdb.org/t/p/w500/8XNsPycPvBVdNohZ2eZrTA99sYp.jpg",
  "imdb_id": "tt0250745",
  "id": 632644,
  "type": "movie"
}