{
  "title": "Little Black Dress",
  "release_date": "2011-01-22",
  "vote_average": 5.5,
  "genres": "Drama, Comedy",
  "overview": "Little Black Dress depicts the friendships, jealousies, hopes and failures of four 24-year-old girls. The girls first met as first year students in college. They seem to be enjoying their 20's, but inside they all have worries.",
  "poster_path": "https://image.tmdb.org/t/p/w500/bjhFHMsMy4gaLSs8LwBRvoT3yYm.jpg",
  "imdb_id": "tt1964895",
  "id": 64846,
  "type": "movie"
}