{
  "title": "Ticket Coffee Shop 2",
  "release_date": "2019-12-26",
  "vote_average": 0,
  "genres": "Romance",
  "overview": "Jae-wook visits the boxing club run by Seung-tae. He takes Seung-tae to a 'fun' place called the Ticket Coffee Shop. Jae-wook calls in a girl named Ji-soo to meet Seung-tae. Ji-soo feels attracted to Seung-tae who's never been to a place like this. Seung-tae goes back the next day, because he can't stop thinking about Ji-soo...",
  "poster_path": "https://image.tmdb.org/t/p/w500/dJf4Epe5w6DLpt0HzKcl0XHotOM.jpg",
  "imdb_id": null,
  "id": 664040,
  "type": "movie"
}