{
  "title": "Kick the Moon",
  "release_date": "2001-06-23",
  "vote_average": 5.95,
  "genres": "Comedy, Drama",
  "overview": "Choi Ki-dong, who becomes a teacher, and Park Young-jun, who becomes a gang member, meet again after 10 years. To compete for Min Ju-ran, they start a fierce battle remembering their high school days, when the situation was completely different.",
  "poster_path": "https://image.tmdb.org/t/p/w500/7qOJ4oAYcxXPeo6zwj7cv1Kf61e.jpg",
  "imdb_id": "tt0294916",
  "id": 68529,
  "type": "movie"
}