{
  "title": "Chu Kat Gaya",
  "release_date": "2020-03-18",
  "vote_average": 0,
  "genres": "Romance",
  "overview": "A Group Of 4 Youngsters One Evening Tempted By Watching Adult Films Decide To Call An Escort To Their Home. Excited And Eagerly Waiting For Her, They All Start To Imagine Her Before She Even Arrives. Upon Arriving She Makes Her Charges Very Clear And Waits For Them In The Bedroom And They Have To Decide Who Is Going First. Watch The Fun As They All Want To Show Off Their Manhood In Front Of Each Other And What Goes Up And Down In The Bedroom.",
  "poster_path": "https://image.tmdb.org/t/p/w500/dnT0t0bAQn6N0oo0goQNWDF9GvD.jpg",
  "imdb_id": "tt12235304",
  "id": 714625,
  "type": "movie"
}