{
  "title": "Ramkinkar Baij",
  "release_date": "1975-01-01",
  "vote_average": 0,
  "genres": "Documentary",
  "overview": "Ramkinkar Baij is an incomplete personality study or documentary on sculptor Ramkinkar Baij created by legendary filmmaker Ritwik Ghatak. He started creating the film in 1975. The film was almost complete but it still remained unfinished for the death of Ritwik Ghatak.",
  "poster_path": "https://image.tmdb.org/t/p/w500/i3MkC9wrlikXpWoWxbExLYrOZWU.jpg",
  "imdb_id": "tt0073603",
  "id": 727259,
  "type": "movie"
}