{
  "title": "War of the Worlds",
  "release_date": "2025-07-29",
  "vote_average": 9,
  "genres": "Science Fiction, Thriller",
  "overview": "Will Radford is a top cyber-security analyst for Homeland Security who tracks potential threats to national security through a mass surveillance program, until one day an attack by an unknown entity leads him to question whether the government is hiding something from him... and from the rest of the world.",
  "poster_path": "https://image.tmdb.org/t/p/w500/tlqTdabozTVjWEPWUhDRITxKt6R.jpg",
  "imdb_id": "tt13186306",
  "id": 755898,
  "type": "movie"
}