{
  "title": "Mem-didi",
  "release_date": "1961-01-01",
  "vote_average": 4.8,
  "genres": "Drama, Comedy",
  "overview": "Memdidi tells a simple and endearing story of Mrs. Roy (Memdidi), who moves in as a new neighbor to the two local tough guys, Bahadur Singh (David) and Sher Khan (Jayant), with a heart of gold.  Hrishikesh Mukherjee's direction and screenplay makes this movie a gem and worth watching again and again.",
  "poster_path": "https://image.tmdb.org/t/p/w500/eNlRhS64PPuFLAmRmbRBbVqTaxC.jpg",
  "imdb_id": "tt0055164",
  "id": 83009,
  "type": "movie"
}