{
  "title": "Buttman & Rocco's Brazilian Butt Fest",
  "release_date": "2001-02-05",
  "vote_average": 0,
  "genres": "",
  "overview": "This year, my Brazilian partner, Stanlay Miranda insisted that I make another video in Brazil during Carnival! (I've been too damn busy the last few years to do one.) So Stanlay flew Rocco and Cassandra Wild in from Europe, and we invited Nacho Vidal and Jasmine to come in from Spain... plus me, Hatman and Joey flew in from America! The only requirement was that we behave like Brazilians during Carnival!",
  "poster_path": "https://image.tmdb.org/t/p/w500/enXbPQdWw2JXRKCTdywdF92sdBN.jpg",
  "imdb_id": null,
  "id": 924338,
  "type": "movie"
}