{
  "title": "Killer Desire",
  "release_date": "2007-02-06",
  "vote_average": 0,
  "genres": "",
  "overview": "Young, beautiful, seductive, and absolutely deadly. Enter the world of high stakes contract killers with Club Jenna contract star Brea Bennett where the lines between nihilistic fantasies blur, Killer Desire heightens the thrill, and each passionate embrace could be your last! What price are you willing to pay for the ultimate sexual rush with one of the world's most beautiful women? Be careful what you wish for... you just might get it!",
  "poster_path": "https://image.tmdb.org/t/p/w500/mi3Ge3fSbXLQvWkV4svFxjpOlNb.jpg",
  "imdb_id": "tt0967517",
  "id": 93830,
  "type": "movie"
}