{
  "title": "S.O.Z: Soldiers or Zombies",
  "release_date": "2021-08-06",
  "vote_average": 7.146,
  "genres": "Drama, Sci-Fi & Fantasy",
  "overview": "Drug lord Alonso Marroquín escapes from a Mexican prison in an attempt to go into hiding. A US military secret experiment goes wrong and the elite unit from the Mexican Police that is after Marroquín gets infected, creating a new zombie species. The Army and the zombies end up at the drug lord’s hideout and a battle for human survival begins.",
  "poster_path": "https://image.tmdb.org/t/p/w500/arYdHX708nDq6oWNOSjw6NczWc5.jpg",
  "imdb_id": "NO ID",
  "id": 95281,
  "type": "tv"
}