{
  "title": "Quaid-e-Azam Zindabad",
  "release_date": "2022-07-08",
  "vote_average": 8,
  "genres": "Action, Comedy",
  "overview": "The idea of \"showing money and getting things done\" is widespread. Gulab Mughal is the son of an honest policeman and grew up watching his father walk the right path, but it's not the path to happiness. Activist Jia has even worse plans for illegal money in the country.",
  "poster_path": "https://image.tmdb.org/t/p/w500/dqgzgpB9nynNEjY5445EhMG8zn9.jpg",
  "imdb_id": "tt12138574",
  "id": 958552,
  "type": "movie"
}