{
  "title": "Hot staff: Kaikan sex kurinikku",
  "release_date": "1987-07-04",
  "vote_average": 2,
  "genres": "Drama",
  "overview": "One day, a man who is sexually impotent (only with his wife) ends up switching places with a sex counselor who looks exactly like him. Depicts a \"love story\" between husbands and wives with a lot of twists and turns.",
  "poster_path": "https://image.tmdb.org/t/p/w500/e79oGCmBI8dQ0TItHRBChwPvt6Z.jpg",
  "imdb_id": "tt10365688",
  "id": 958839,
  "type": "movie"
}