{
  "title": "The Kinky Coaches and the Pom Pom Pussycats",
  "release_date": "1981-08-28",
  "vote_average": 0,
  "genres": "Comedy",
  "overview": "Two long-time rival high school football coaches lead their respective teams into battle for the city football championship. However, before the opening kickoff, various students from each school try to do whatever it takes to throw the opposing team off of their game.",
  "poster_path": "https://image.tmdb.org/t/p/w500/turUJqDpNu3Tv2rK4kjdGIwFVpU.jpg",
  "imdb_id": "tt0081001",
  "id": 98137,
  "type": "movie"
}