{
  "title": "Grandma's Boy",
  "release_date": "2006-01-06",
  "vote_average": 6.5,
  "genres": "Comedy",
  "overview": "Even though he's 35, Alex acts more like he's 13, spending his days as the world's oldest video game tester and his evenings developing the next big Xbox game. But when he gets kicked out of his apartment, he's forced to move in with his grandmother.",
  "poster_path": "https://image.tmdb.org/t/p/w500/fSRdHBtisU0zhks4OjKezI3jnt7.jpg",
  "imdb_id": "tt0456554",
  "id": 9900,
  "type": "movie"
}