{
  "title": "Her First Lesbian Sex 17",
  "release_date": "2009-10-30",
  "vote_average": 0,
  "genres": "",
  "overview": "Tasty twats get tongued and turned out by luscious lesbians going down on frisky first-timers Bi-curious cunts get brutalized as the all-girl amateurs feel the orgasmic rush of having their sweet tits and wet pussies worked by a fellow femme.",
  "poster_path": "https://image.tmdb.org/t/p/w500/rL1aDT5QGKBB94Hyu9GFm5n9J3G.jpg",
  "imdb_id": null,
  "id": 991793,
  "type": "movie"
}